LICENSE
README.md
setup.py
sentify/__init__.py
sentify/config.py
sentify/main.py
sentify/requirements.txt
sentify/segmenter.py
sentify/tools.py
sentify/wikifetch.py
sentify.egg-info/PKG-INFO
sentify.egg-info/SOURCES.txt
sentify.egg-info/dependency_links.txt
sentify.egg-info/not-zip-safe
sentify.egg-info/requires.txt
sentify.egg-info/top_level.txt
tests/tests.py