Metadata-Version: 2.4
Name: sentify
Version: 1.0.2
Summary: Converter from urls,pdfs,wikipages to clean text document one sentence per line.
Home-page: https://github.com/ptarau/sentify.git
Author: Paul Tarau
Author-email: ptarau@gmail.com
License: MIT
License-File: LICENSE
Requires-Dist: pdfminer.six
Requires-Dist: smart_open
Requires-Dist: Wikipedia-API
Requires-Dist: twine
Requires-Dist: pysbd
Requires-Dist: python-docx
Requires-Dist: openpyxl
Requires-Dist: pandas
Dynamic: author
Dynamic: author-email
Dynamic: description
Dynamic: description-content-type
Dynamic: home-page
Dynamic: license
Dynamic: license-file
Dynamic: requires-dist
Dynamic: summary
